ff_cache/__init__.py
ff_cache/cache.py
ff_cache/constant.py
ff_cache/context.py
ff_cache/decorator.py
ff_cache/functions.py
ff_cache/memory_cache.py
ff_cache/serializer.py
ff_cache/asyncio/__init__.py
ff_cache/asyncio/cache.py
ff_cache/asyncio/decorator.py
ff_cache/redis/__init__.py
ff_cache/redis/async_cache.py
ff_cache/redis/cache.py
ff_cache-0.2.0.dist-info/METADATA
ff_cache-0.2.0.dist-info/WHEEL
ff_cache-0.2.0.dist-info/top_level.txt
ff_cache-0.2.0.dist-info/RECORD
